pseud/__init__.py
pseud/auth.py
pseud/client.py
pseud/common.py
pseud/heartbeat.py
pseud/interfaces.py
pseud/packer.py
pseud/predicate.py
pseud/server.py
pseud/utils.py
pseud-1.0.1.dist-info/METADATA
pseud-1.0.1.dist-info/RECORD
pseud-1.0.1.dist-info/WHEEL
pseud-1.0.1.dist-info/top_level.txt
pseud-1.0.1.dist-info/zip-safe
